unitplus/__init__.py
unitplus/case.py
unitplus/cli.py
unitplus/filter.py
unitplus/result.py
unitplus/runner.py
unitplus/suite.py
unitplus/testplan.py
unitplus/unitplus.py
unitplus-0.1.0.dist-info/AUTHORS.rst
unitplus-0.1.0.dist-info/LICENSE
unitplus-0.1.0.dist-info/METADATA
unitplus-0.1.0.dist-info/WHEEL
unitplus-0.1.0.dist-info/entry_points.txt
unitplus-0.1.0.dist-info/top_level.txt
unitplus-0.1.0.dist-info/RECORD
