Metadata-Version: 2.1
Name: unitplus
Version: 0.1.0
Summary: unittest enhancement
Home-page: https://github.com/hanzhichao/unitplus
Author: Han Zhichao
Author-email: superhin@126.com
License: MIT license
Keywords: unitplus
Classifier: Development Status :: 2 - Pre-Alpha
Classifier: Intended Audience :: Developers
Classifier: License :: OSI Approved :: MIT License
Classifier: Natural Language :: English
Classifier: Programming Language :: Python :: 3
Classifier: Programming Language :: Python :: 3.6
Classifier: Programming Language :: Python :: 3.7
Classifier: Programming Language :: Python :: 3.8
Requires-Python: >=3.6
License-File: LICENSE
License-File: AUTHORS.rst
